Workbook

Sheet Index Sheet
B2: Baseline Rate Card
B3: Experience Multiplier
B4: Location Multiplier
B5: Currency Exchange
B6: Monthly Rate Card
B7: Business Type Multiplier
B8: Discount Rates
B9: Scope Complexity
B10: SLA
B11: Risk Buffer
B12: Contingency

Sheet Risk vs Contingency
B2: Risk Buffer
C3: Purpose: Covers known uncertainties that could affect effort or cost.
C4: Examples: Scope creep, dependency delays, client-side approvals.
C5: When applied: After calculating base cost, before discount.
C6: Typical range: +5% to +15%.
C7: Why needed: Protects margin when predictable risks materialize.
B9: Contingency
C10: Purpose: Covers unknown or unforeseen events that cannot be predicted upfront.
C11: Examples: Regulatory changes, sudden compliance audits, unexpected environment failures.
C12: When applied: At the very end, after risk buffer and discount.
C13: Typical range: +3% to +10%.
C14: Why needed: Ensures sustainability without renegotiation when surprises occur.
B16: Why both?
C17: Risk Buffer = planned for known risks (we expect them, but not sure when/how).
C18: Contingency = planned for unknown risks (we don’t know what, but something might happen).
C20: If you skip one:
C21: Without Risk Buffer, you’ll lose margin on predictable issues.
C22: Without Contingency, you’ll scramble for budget when unexpected events hit.
B24: Best Practice:
C25: Use Risk Buffer for project-specific uncertainties.
C26: Use Contingency for organizational or external unknowns.
C27: Keep them separate for transparency in client proposals.

Sheet Pricing Calculator
A1: Input | G1: Output
B2: Metric | C2: ID | D2: Particulars | E2: Value | F2: Notes | H2: Metric | I2: Value | J2: Notes
B3: Baseline Rate | C3: Baseline - 1 | D3: =_xlfn.XLOOKUP(C3,'Baseline Rate Card'!A:A,'Baseline Rate Card'!B:B) -> API Integration | E3: =_xlfn.XLOOKUP(C3,'Baseline Rate Card'!A:A,'Baseline Rate Card'!C:C) -> 110 | F3: From Baselines sheet | H3: Adjusted Junior | I3: =E3*E4*E7*E8*E10*E11 -> 57.75 | J3: Baseline * Junior multiplier × all multipliers
B4: Experience Multiplier - Junior Rate | C4: EMJ 1 | D4: =_xlfn.XLOOKUP(C4,'Experience Multiplier'!A:A,'Experience Multiplier'!B:B) -> Experience Muliplier 1 | E4: =_xlfn.XLOOKUP(C4,'Experience Multiplier'!A:A,'Experience Multiplier'!D:D) -> 0.7 | F4: Baseline × Junior multiplier | H4: Adjusted Mid | I4: =E3*E5*E7*E8*E10*E11 -> 82.5 | J4: Baseline * Mid multiplier × all multipliers
B5: Experience Multiplier - Mid Rate | C5: EMM 1 | D5: =_xlfn.XLOOKUP(C5,'Experience Multiplier'!A:A,'Experience Multiplier'!B:B) -> Experience Muliplier 1 | E5: =_xlfn.XLOOKUP(C5,'Experience Multiplier'!A:A,'Experience Multiplier'!D:D) -> 1 | F5: Baseline × Mid multiplier | H5: Adjusted Senior | I5: =E3*E6*E7*E8*E10*E11 -> 115.5 | J5: Baseline * Senior multiplier × all multipliers
B6: Experience Multiplier - Senior Rate | C6: EMS 1 | D6: =_xlfn.XLOOKUP(C6,'Experience Multiplier'!A:A,'Experience Multiplier'!B:B) -> Experience Muliplier 1 | E6: =_xlfn.XLOOKUP(C6,'Experience Multiplier'!A:A,'Experience Multiplier'!D:D) -> 1.4 | F6: Baseline × Senior multiplier | H6: Rate with Risk - Junior | I6: =I3+(I3*E16) -> 57.8655 | J6: Apply Risk% - Junior
B7: Location Multiplier | C7: LMIOF 1 | D7: =_xlfn.XLOOKUP('Pricing Calculator'!C7,'Location Multiplier'!A:A,'Location Multiplier'!C:C) -> India Offshore | E7: =_xlfn.XLOOKUP('Pricing Calculator'!C7,'Location Multiplier'!A:A,'Location Multiplier'!D:D) -> 0.75 | F7: Selected location multiplier | H7: Rate with Risk - Mid | I7: =I4+(I4*E16) -> 82.665 | J7: Apply Risk% - Mid
B8: Business Type Multiplier | C8: BT1 | D8: =_xlfn.XLOOKUP(C8,'Business Type Multiplier'!A:A,'Business Type Multiplier'!B:B) -> Standard Rate | E8: =_xlfn.XLOOKUP(C8,'Business Type Multiplier'!A:A,'Business Type Multiplier'!C:C) -> 1 | F8: Selected business type multiplier | H8: Rate with Risk - Senior | I8: =I5+(I5*E16) -> 115.731 | J8: Apply Risk% - Senior
B9: Scope Complexity Multiplier | C9: SC 1 | D9: =_xlfn.XLOOKUP(C9,'Scope Complexity'!A:A,'Scope Complexity'!B:B) -> Low | E9: =_xlfn.XLOOKUP(C9,'Scope Complexity'!A:A,'Scope Complexity'!C:C) -> 0.95 | F9: Selected scope complexity multiplier | H9: Rate after Discount - Junior | I9: =I6-(I6*E17) -> 57.807634 | J9: Apply discount
B10: SLAs Multiplier | C10: SLA 1 | D10: =_xlfn.XLOOKUP(C10,SLA!A:A,SLA!B:B) -> Business Hours | E10: =_xlfn.XLOOKUP(C10,SLA!A:A,SLA!C:C) -> 1 | F10: Selected SLA multiplier | H10: Rate after Discount - Mid | I10: =I7-(I7*E17) -> 82.582335 | J10: Apply discount
B11: Currency | C11: Nov-25 USD | D11: =_xlfn.XLOOKUP(C11,'Currency Exchange'!A:A,'Currency Exchange'!C:C) -> USD | E11: =_xlfn.XLOOKUP(C11,'Currency Exchange'!A:A,'Currency Exchange'!D:D) -> 1 | F11: Selected Currency | H11: Rate after Discount - Senior | I11: =I8-(I8*E17) -> 115.61527 | J11: Apply discount
B12: Rate card Type Hourly / Daily / Monthly / Sprint wise / Milestone | C12: Hour | D12: =_xlfn.XLOOKUP(C12,'Monthly Rate Card'!A:A,'Monthly Rate Card'!A:A) -> Hour | E12: =_xlfn.XLOOKUP(C12,'Monthly Rate Card'!A:A,'Monthly Rate Card'!B:B) -> 1 | F12: Rate card Type Hourly / Daily / Monthy / Sprint wise / Milestone | H12: Final Rate - Junior | I12: =I9+(I9*E16) -> 57.92325 | J12: Add contingency
B13: Junior % | C13: BRJ1 | D13: =_xlfn.XLOOKUP(C13,'Blended Rate'!A:A,'Blended Rate'!B:B) -> Junior | E13: =_xlfn.XLOOKUP(C13,'Blended Rate'!A:A,'Blended Rate'!C:C) -> 0.3 | F13: Selected Junior% Mix | H13: Final Rate - Mid | I13: =I10+(I10*E16) -> 82.7475 | J13: Add contingency
B14: Mid% | C14: BRM2 | D14: =_xlfn.XLOOKUP(C14,'Blended Rate'!A:A,'Blended Rate'!B:B) -> Mid | E14: =_xlfn.XLOOKUP(C14,'Blended Rate'!A:A,'Blended Rate'!C:C) -> 0.5 | F14: Selected Mid% Mix | H14: Final Rate - Senior | I14: =I11+(I11*E16) -> 115.8465 | J14: Add contingency
B15: Senior % | C15: BRS3 | D15: =_xlfn.XLOOKUP(C15,'Blended Rate'!A:A,'Blended Rate'!B:B) -> Senior | E15: =_xlfn.XLOOKUP(C15,'Blended Rate'!A:A,'Blended Rate'!C:C) -> 0.2 | F15: Selected Senior% Mix | H15: Final Blended Rate | I15: =(I12*E13)+(I13*E14)+(I14*E15) -> 81.920025 | J15: Junior% × Adjusted Junior + Mid% × Adjusted Mid + Senior% × Adjusted Senior
B16: Risk Buffer % | C16: RL3 | D16: =_xlfn.XLOOKUP(C16,'Risk Buffer'!A:A,'Risk Buffer'!B:B) -> Risk Buffer 3 | E16: =_xlfn.XLOOKUP(C16,'Risk Buffer'!A:A,'Risk Buffer'!C:C) -> 0.002 | F16: Input as %
B17: Discount % | C17: DR2 | D17: =_xlfn.XLOOKUP(C17,'Discount Rates'!A:A,'Discount Rates'!B:B) -> Discount 2 | E17: =_xlfn.XLOOKUP(C17,'Discount Rates'!A:A,'Discount Rates'!C:C) -> 0.001 | F17: Input as %
B18: Contingency % | C18: CON 2 | D18: =_xlfn.XLOOKUP(C18,Contingency!A:A,Contingency!B:B) -> Contigency 2 | E18: =_xlfn.XLOOKUP(C18,Contingency!A:A,Contingency!C:C) -> 0.001 | F18: Input as %

Sheet Product List table
A1: Product ID | B1: Product Name | C1: Service ID | D1: Experience Muliplier ID | E1: Location Muliplier ID | F1: Exchange Conversion ID | G1: Business Type ID | H1: Blended Rate ID | I1: Discount rate ID | J1: Scope Complexity ID | K1: SLA ID | L1: Risk Buffer ID | M1: Contingency ID | N1: Rate Card

Sheet Baseline Rate Card
A1: Service ID | B1: Service | C1: Baseline USD/hour | D1: Notes
A2: Baseline - 1 | B2: API Integration | C2: 110 | D2: Mid-level benchmark based on industry averages
A3: Baseline - 2 | B3: Automation Tester | C3: 95 | D3: Mid-level benchmark based on industry averages
A4: Baseline - 3 | B4: Back-end Developer | C4: 105 | D4: Mid-level benchmark based on industry averages
A5: Baseline - 4 | B5: Business Analyst | C5: 90 | D5: Mid-level benchmark based on industry averages
A6: Baseline - 5 | B6: Customer Analytics | C6: 130 | D6: Mid-level benchmark based on industry averages
A7: Baseline - 6 | B7: Customer Journey Analytics | C7: 140 | D7: Mid-level benchmark based on industry averages
A8: Baseline - 7 | B8: Customer LTV Analytics | C8: 140 | D8: Mid-level benchmark based on industry averages
A9: Baseline - 8 | B9: DBA | C9: 110 | D9: Mid-level benchmark based on industry averages
A10: Baseline - 9 | B10: Data Analyst | C10: 95 | D10: Mid-level benchmark based on industry averages
A11: Baseline - 10 | B11: Data Analytics / Visualization | C11: 110 | D11: Mid-level benchmark based on industry averages
A12: Baseline - 11 | B12: Data Engineering | C12: 120 | D12: Mid-level benchmark based on industry averages
A13: Baseline - 12 | B13: Data Migration | C13: 90 | D13: Mid-level benchmark based on industry averages
... A38: Baseline - 37 | B38: Supply Chain Analytics | C38: 140 | D38: Mid-level benchmark based on industry averages

Sheet Experience Multiplier
A1: Experience Muliplier ID | B1: Experience Muliplier Name | C1: Experience Level | D1: Rate Card | E1: Notes
A2: EMJ 1 | B2: Experience Muliplier 1 | C2: Junior | D2: 0.7 | E2: Experience Level Multiplier from Baseline Rate
A3: EMM 1 | B3: Experience Muliplier 1 | C3: Mid | D3: 1 | E3: Experience Level Multiplier from Baseline Rate
A4: EMS 1 | B4: Experience Muliplier 1 | C4: Senior | D4: 1.4 | E4: Experience Level Multiplier from Baseline Rate
A5: EMJ 2 | B5: Experience Muliplier 2 | C5: Junior | D5: 0.65 | E5: Experience Level Multiplier from Baseline Rate
A6: EMM 2 | B6: Experience Muliplier 2 | C6: Mid | D6: 0.95 | E6: Experience Level Multiplier from Baseline Rate
A7: EMS 2 | B7: Experience Muliplier 2 | C7: Senior | D7: 1.35 | E7: Experience Level Multiplier from Baseline Rate
A8: EMJ 3 | B8: Experience Muliplier 3 | C8: Junior | D8: 0.75 | E8: Experience Level Multiplier from Baseline Rate
A9: EMM 3 | B9: Experience Muliplier 3 | C9: Mid | D9: 1.1 | E9: Experience Level Multiplier from Baseline Rate
A10: EMS 3 | B10: Experience Muliplier 3 | C10: Senior | D10: 1.5 | E10: Experience Level Multiplier from Baseline Rate

Sheet Location Multiplier
A1: Location Muliplier ID | B1: Location Muliplier Name | C1: Location | D1: Rate Card | E1: Notes
A2: LMIOF 1 | B2: Location Muliplier 1 | C2: India Offshore | D2: 0.75 | E2: Location wise multiplier is used to derived the final rates based on baseline rate card
A3: LMION 1 | B3: Location Muliplier 1 | C3: India Onsite | D3: 0.9 | E3: Location wise multiplier is used to derived the final rates based on baseline rate card
A4: LMOON 1 | B4: Location Muliplier 1 | C4: Overseas Onsite | D4: 1.15 | E4: Location wise multiplier is used to derived the final rates based on baseline rate card
A5: LMIOF 2 | B5: Location Muliplier 2 | C5: India Offshore | D5: 0.7 | E5: Location wise multiplier is used to derived the final rates based on baseline rate card
A6: LMION 2 | B6: Location Muliplier 2 | C6: India Onsite | D6: 1.85 | E6: Location wise multiplier is used to derived the final rates based on baseline rate card
A7: LMOON 2 | B7: Location Muliplier 2 | C7: Overseas Onsite | D7: 1.1 | E7: Location wise multiplier is used to derived the final rates based on baseline rate card
A8: LMIOF 3 | B8: Location Muliplier 3 | C8: India Offshore | D8: 0.65 | E8: Location wise multiplier is used to derived the final rates based on baseline rate card
A9: LMION 3 | B9: Location Muliplier 3 | C9: India Onsite | D9: 0.8 | E9: Location wise multiplier is used to derived the final rates based on baseline rate card
A10: LMOON 3 | B10: Location Muliplier 3 | C10: Overseas Onsite | D10: 1 | E10: Location wise multiplier is used to derived the final rates based on baseline rate card

Sheet Currency Exchange
A1: Exchange Conversion ID | B1: Month | C1: Currency | D1: Conversion Rate (per 1 USD) | E1: Notes
A2: =CONCATENATE("Nov-25"," ",FXRates[[#This Row],[Currency]]) -> Nov-25 USD | B2: 45989 | C2: USD | D2: 1 | E2: Currency rates are as of 28th Nov 2025
A3: =CONCATENATE("Nov-25"," ",FXRates[[#This Row],[Currency]]) -> Nov-25 INR | B3: 45989 | C3: INR | D3: 85 | E3: Currency rates are as of 28th Nov 2025
A4: =CONCATENATE("Nov-25"," ",FXRates[[#This Row],[Currency]]) -> Nov-25 SAR | B4: 45989 | C4: SAR | D4: 3.75 | E4: Currency rates are as of 28th Nov 2025
A5: =CONCATENATE("Nov-25"," ",FXRates[[#This Row],[Currency]]) -> Nov-25 AED | B5: 45989 | C5: AED | D5: 3.67 | E5: Currency rates are as of 28th Nov 2025
A6: =CONCATENATE("Nov-25"," ",FXRates[[#This Row],[Currency]]) -> Nov-25 GBP | B6: 45989 | C6: GBP | D6: 0.78 | E6: Currency rates are as of 28th Nov 2025
A7: =CONCATENATE("Nov-25"," ",FXRates[[#This Row],[Currency]]) -> Nov-25 EUR | B7: 45989 | C7: EUR | D7: 0.92 | E7: Currency rates are as of 28th Nov 2025
A8: =CONCATENATE("Nov-25"," ",FXRates[[#This Row],[Currency]]) -> Nov-25 AUD | B8: 45989 | C8: AUD | D8: 1.55 | E8: Currency rates are as of 28th Nov 2025
A9: =CONCATENATE("Nov-25"," ",FXRates[[#This Row],[Currency]]) -> Nov-25 NZD | B9: 45989 | C9: NZD | D9: 1.7 | E9: Currency rates are as of 28th Nov 2025
A10: =CONCATENATE("Nov-25"," ",FXRates[[#This Row],[Currency]]) -> Nov-25 SGD | B10: 45989 | C10: SGD | D10: 1.35 | E10: Currency rates are as of 28th Nov 2025
A11: =CONCATENATE("Nov-25"," ",FXRates[[#This Row],[Currency]]) -> Nov-25 MXN | B11: 45989 | C11: MXN | D11: 17 | E11: Currency rates are as of 28th Nov 2025
A12: =CONCATENATE("Nov-25"," ",FXRates[[#This Row],[Currency]]) -> Nov-25 ZAR | B12: 45989 | C12: ZAR | D12: 18.5 | E12: Currency rates are as of 28th Nov 2025
A13: =CONCATENATE("Nov-25"," ",FXRates[[#This Row],[Currency]]) -> Nov-25 MYR | B13: 45989 | C13: MYR | D13: 4.7 | E13: Currency rates are as of 28th Nov 2025
... A18: =CONCATENATE("Nov-25"," ",FXRates[[#This Row],[Currency]]) -> Nov-25 ARS | B18: 45989 | C18: ARS | D18: 350 | E18: Currency rates are as of 28th Nov 2025

Sheet Monthly Rate Card
A1: Type of Rate Card | B1: Conversion | C1: Notes
A2: Hour | B2: 1 | C2: Rates mentioned in hours, for a day its 8 Hours
A3: Daily | B3: 8 | C3: Rates mentioned in hours, for a day its 8 Hours
A4: Monthly 1 | B4: =19*8 -> 152 | C4: Rates mentioned in hours, for a day its 8 Hours
A5: Monthly 2 | B5: =20*8 -> 160 | C5: Rates mentioned in hours, for a day its 8 Hours
A6: Monthly 3 | B6: =18*8 -> 144 | C6: Rates mentioned in hours, for a day its 8 Hours
A7: Sprint wise 1 | B7: =7*8 -> 56 | C7: Rates mentioned in hours, for a day its 8 Hours
A8: Sprint wise 2 | B8: =14*8 -> 112 | C8: Rates mentioned in hours, for a day its 8 Hours
A9: Sprint wise 3 | B9: =6*8 -> 48 | C9: Rates mentioned in hours, for a day its 8 Hours
A10: Sprint wise 4 | B10: =12*8 -> 96 | C10: Rates mentioned in hours, for a day its 8 Hours
A11: Sprint wise 5 | B11: =5*8 -> 40 | C11: Rates mentioned in hours, for a day its 8 Hours
A12: Sprint wise 6 | B12: =10*8 -> 80 | C12: Rates mentioned in hours, for a day its 8 Hours
A13: Milestone Based 1 | B13: =30*8 -> 240 | C13: Rates mentioned in hours, for a day its 8 Hours
A14: Milestone Based 2 | B14: =45*8 -> 360 | C14: Rates mentioned in hours, for a day its 8 Hours
A15: Milestone Based 3 | B15: =60*8 -> 480 | C15: Rates mentioned in hours, for a day its 8 Hours

Sheet Business Type Multiplier
A1: Business Type ID | B1: Type of Companies | C1: Conversion | D1: Notes
A2: BT1 | B2: Standard Rate | C2: 1 | D2: Typical projects, moderate governance, standard SLAs
A3: BT2 | B3: Small Business | C3: 0.9 | D3: Price-sensitive, smaller scope, lighter compliance
A4: BT3 | B4: Medium Business | C4: 1.05 | D4: Growing needs, some compliance & reporting, occasional onsite
A5: BT4 | B5: Enterprise Business | C5: 1.2 | D5: Complex integration, strict governance/compliance, higher SLA commitments
A6: BT5 | B6: Large MNCs | C6: 1.35 | D6: Multi-region, 24×7 support, security audits, global templates, heavier PMO & vendor management
A7: BT6 | B7: Default Rate | C7: 0.85 | D7: Default Rate uses for leads time when revenue is not known

Sheet Blended Rate
A1: Blended Rate ID | B1: Type of Role | C1: Conversion | D1: Notes
A2: BRJ1 | B2: Junior | C2: 0.3 | D2: Blended Rate Mix, if Blended Rate card provided
A3: BRM2 | B3: Mid | C3: 0.5 | D3: Blended Rate Mix, if Blended Rate card provided
A4: BRS3 | B4: Senior | C4: 0.2 | D4: Blended Rate Mix, if Blended Rate card provided

Sheet Discount Rates
A1: Discount rate ID | B1: Name of Discount | C1: Discount | D1: Notes
A2: DR1 | B2: Discount 1 | C2: 0 | D2: Various discount multiplier. Applied after risk buffer
A3: DR2 | B3: Discount 2 | C3: 0.001 | D3: Various discount multiplier. Applied after risk buffer
A4: DR3 | B4: Discount 3 | C4: 0.002 | D4: Various discount multiplier. Applied after risk buffer
A5: DR4 | B5: Discount 4 | C5: 0.003 | D5: Various discount multiplier. Applied after risk buffer
A6: DR5 | B6: Discount 5 | C6: 0.004 | D6: Various discount multiplier. Applied after risk buffer
A7: DR6 | B7: Discount 6 | C7: 0.005 | D7: Various discount multiplier. Applied after risk buffer
A8: DR7 | B8: Discount 7 | C8: 0.006 | D8: Various discount multiplier. Applied after risk buffer
A9: DR8 | B9: Discount 8 | C9: 0.007 | D9: Various discount multiplier. Applied after risk buffer
A10: DR9 | B10: Discount 9 | C10: 0.008 | D10: Various discount multiplier. Applied after risk buffer
A11: DR10 | B11: Discount 10 | C11: 0.009 | D11: Various discount multiplier. Applied after risk buffer
A12: DR11 | B12: Discount 11 | C12: 0.01 | D12: Various discount multiplier. Applied after risk buffer
A13: DR12 | B13: Discount 12 | C13: 0.011 | D13: Various discount multiplier. Applied after risk buffer
... A1002: DR1001 | B1002: Discount 1001 | C1002: 1 | D1002: Various discount multiplier. Applied after risk buffer

Sheet Scope Complexity
A1: Scope Complexity ID | B1: Scope Complexity | C1: Multiplier | D1: Notes
A2: SC 1 | B2: Low | C2: 0.95 | D2: Complexity of scope & integrations. What it means - Defines the breadth of work—number of modules, integrations, customizations, environments. Why it matters - Larger or more complex scope requires more effort, coordination, and testing. Impact on pricing - Higher scope complexity → higher multiplier (e.g., Low = 0.95, High = 1.10, Very High = 1.20)
A3: SC 2 | B3: Medium | C3: 1 | D3: Complexity of scope & integrations. What it means - Defines the breadth of work—number of modules, integrations, customizations, environments. Why it matters - Larger or more complex scope requires more effort, coordination, and testing. Impact on pricing - Higher scope complexity → higher multiplier (e.g., Low = 0.95, High = 1.10, Very High = 1.20)
A4: SC 3 | B4: High | C4: 1.1 | D4: Complexity of scope & integrations. What it means - Defines the breadth of work—number of modules, integrations, customizations, environments. Why it matters - Larger or more complex scope requires more effort, coordination, and testing. Impact on pricing - Higher scope complexity → higher multiplier (e.g., Low = 0.95, High = 1.10, Very High = 1.20)
A5: SC 4 | B5: Very High | C5: 1.2 | D5: Complexity of scope & integrations. What it means - Defines the breadth of work—number of modules, integrations, customizations, environments. Why it matters - Larger or more complex scope requires more effort, coordination, and testing. Impact on pricing - Higher scope complexity → higher multiplier (e.g., Low = 0.95, High = 1.10, Very High = 1.20)

Sheet SLA
A1: SLA ID | B1: SLA levels | C1: Multiplier | D1: Notes
A2: SLA 1 | B2: Business Hours | C2: 1 | D2: Support hours & SLA severity. What it means : Commitments on uptime, response time, and support hours (e.g., Business Hours vs 24×7). Why it matters: Stricter SLAs require more staffing, monitoring, and escalation readiness. Impact on pricing: Higher SLA severity → higher multiplier (e.g., Business Hours = 1.00, 24×7 = 1.15).
A3: SLA 2 | B3: Extended Hours | C3: 1.08 | D3: Support hours & SLA severity. What it means : Commitments on uptime, response time, and support hours (e.g., Business Hours vs 24×7). Why it matters: Stricter SLAs require more staffing, monitoring, and escalation readiness. Impact on pricing: Higher SLA severity → higher multiplier (e.g., Business Hours = 1.00, 24×7 = 1.15).
A4: SLA 3 | B4: 24x7 | C4: 1.15 | D4: Support hours & SLA severity. What it means : Commitments on uptime, response time, and support hours (e.g., Business Hours vs 24×7). Why it matters: Stricter SLAs require more staffing, monitoring, and escalation readiness. Impact on pricing: Higher SLA severity → higher multiplier (e.g., Business Hours = 1.00, 24×7 = 1.15).

Sheet Risk Buffer
A1: Risk Buffer ID | B1: Risk Buffer | C1: Multiplier | D1: Notes
A2: RL1 | B2: Risk Buffer 1 | C2: 0 | D2: Applied to subtotal (excludes discount). What it means : Extra margin to cover uncertainties—scope creep, dependency delays, client-side delays. Why it matters : Protects profitability when unknowns arise. Impact on pricing : Typically +5% to +15% added to subtotal before discount.
A3: RL2 | B3: Risk Buffer 2 | C3: 0.001 | D3: Applied to subtotal (excludes discount). What it means : Extra margin to cover uncertainties—scope creep, dependency delays, client-side delays. Why it matters : Protects profitability when unknowns arise. Impact on pricing : Typically +5% to +15% added to subtotal before discount.
A4: RL3 | B4: Risk Buffer 3 | C4: 0.002 | D4: Applied to subtotal (excludes discount). What it means : Extra margin to cover uncertainties—scope creep, dependency delays, client-side delays. Why it matters : Protects profitability when unknowns arise. Impact on pricing : Typically +5% to +15% added to subtotal before discount.
A5: RL4 | B5: Risk Buffer 4 | C5: 0.003 | D5: Applied to subtotal (excludes discount). What it means : Extra margin to cover uncertainties—scope creep, dependency delays, client-side delays. Why it matters : Protects profitability when unknowns arise. Impact on pricing : Typically +5% to +15% added to subtotal before discount.
A6: RL5 | B6: Risk Buffer 5 | C6: 0.004 | D6: Applied to subtotal (excludes discount). What it means : Extra margin to cover uncertainties—scope creep, dependency delays, client-side delays. Why it matters : Protects profitability when unknowns arise. Impact on pricing : Typically +5% to +15% added to subtotal before discount.
A7: RL6 | B7: Risk Buffer 6 | C7: 0.005 | D7: Applied to subtotal (excludes discount). What it means : Extra margin to cover uncertainties—scope creep, dependency delays, client-side delays. Why it matters : Protects profitability when unknowns arise. Impact on pricing : Typically +5% to +15% added to subtotal before discount.
A8: RL7 | B8: Risk Buffer 7 | C8: 0.006 | D8: Applied to subtotal (excludes discount). What it means : Extra margin to cover uncertainties—scope creep, dependency delays, client-side delays. Why it matters : Protects profitability when unknowns arise. Impact on pricing : Typically +5% to +15% added to subtotal before discount.
A9: RL8 | B9: Risk Buffer 8 | C9: 0.007 | D9: Applied to subtotal (excludes discount). What it means : Extra margin to cover uncertainties—scope creep, dependency delays, client-side delays. Why it matters : Protects profitability when unknowns arise. Impact on pricing : Typically +5% to +15% added to subtotal before discount.
A10: RL9 | B10: Risk Buffer 9 | C10: 0.008 | D10: Applied to subtotal (excludes discount). What it means : Extra margin to cover uncertainties—scope creep, dependency delays, client-side delays. Why it matters : Protects profitability when unknowns arise. Impact on pricing : Typically +5% to +15% added to subtotal before discount.
A11: RL10 | B11: Risk Buffer 10 | C11: 0.009 | D11: Applied to subtotal (excludes discount). What it means : Extra margin to cover uncertainties—scope creep, dependency delays, client-side delays. Why it matters : Protects profitability when unknowns arise. Impact on pricing : Typically +5% to +15% added to subtotal before discount.
A12: RL11 | B12: Risk Buffer 11 | C12: 0.01 | D12: Applied to subtotal (excludes discount). What it means : Extra margin to cover uncertainties—scope creep, dependency delays, client-side delays. Why it matters : Protects profitability when unknowns arise. Impact on pricing : Typically +5% to +15% added to subtotal before discount.
A13: RL12 | B13: Risk Buffer 12 | C13: 0.011 | D13: Applied to subtotal (excludes discount). What it means : Extra margin to cover uncertainties—scope creep, dependency delays, client-side delays. Why it matters : Protects profitability when unknowns arise. Impact on pricing : Typically +5% to +15% added to subtotal before discount.
... A1002: RL1001 | B1002: Risk Buffer 1001 | C1002: 1 | D1002: Applied to subtotal (excludes discount). What it means : Extra margin to cover uncertainties—scope creep, dependency delays, client-side delays. Why it matters : Protects profitability when unknowns arise. Impact on pricing : Typically +5% to +15% added to subtotal before discount.

Sheet Contingency
A1: Contingency ID | B1: Contigency | C1: Multiplier | D1: Notes
A2: CON 1 | B2: Contigency 1 | C2: 0 | D2: Applied at the end for unknowns. What it means : Reserve for unforeseen issues—compliance audits, environment failures, urgent changes. Why it matters : Ensures project sustainability without renegotiation. Impact on pricing: Usually +3% to +10% applied at the end.
A3: CON 2 | B3: Contigency 2 | C3: 0.001 | D3: Applied at the end for unknowns. What it means : Reserve for unforeseen issues—compliance audits, environment failures, urgent changes. Why it matters : Ensures project sustainability without renegotiation. Impact on pricing: Usually +3% to +10% applied at the end.
A4: CON 3 | B4: Contigency 3 | C4: 0.002 | D4: Applied at the end for unknowns. What it means : Reserve for unforeseen issues—compliance audits, environment failures, urgent changes. Why it matters : Ensures project sustainability without renegotiation. Impact on pricing: Usually +3% to +10% applied at the end.
A5: CON 4 | B5: Contigency 4 | C5: 0.003 | D5: Applied at the end for unknowns. What it means : Reserve for unforeseen issues—compliance audits, environment failures, urgent changes. Why it matters : Ensures project sustainability without renegotiation. Impact on pricing: Usually +3% to +10% applied at the end.
A6: CON 5 | B6: Contigency 5 | C6: 0.004 | D6: Applied at the end for unknowns. What it means : Reserve for unforeseen issues—compliance audits, environment failures, urgent changes. Why it matters : Ensures project sustainability without renegotiation. Impact on pricing: Usually +3% to +10% applied at the end.
A7: CON 6 | B7: Contigency 6 | C7: 0.005 | D7: Applied at the end for unknowns. What it means : Reserve for unforeseen issues—compliance audits, environment failures, urgent changes. Why it matters : Ensures project sustainability without renegotiation. Impact on pricing: Usually +3% to +10% applied at the end.
A8: CON 7 | B8: Contigency 7 | C8: 0.006 | D8: Applied at the end for unknowns. What it means : Reserve for unforeseen issues—compliance audits, environment failures, urgent changes. Why it matters : Ensures project sustainability without renegotiation. Impact on pricing: Usually +3% to +10% applied at the end.
A9: CON 8 | B9: Contigency 8 | C9: 0.007 | D9: Applied at the end for unknowns. What it means : Reserve for unforeseen issues—compliance audits, environment failures, urgent changes. Why it matters : Ensures project sustainability without renegotiation. Impact on pricing: Usually +3% to +10% applied at the end.
A10: CON 9 | B10: Contigency 9 | C10: 0.008 | D10: Applied at the end for unknowns. What it means : Reserve for unforeseen issues—compliance audits, environment failures, urgent changes. Why it matters : Ensures project sustainability without renegotiation. Impact on pricing: Usually +3% to +10% applied at the end.
A11: CON 10 | B11: Contigency 10 | C11: 0.009 | D11: Applied at the end for unknowns. What it means : Reserve for unforeseen issues—compliance audits, environment failures, urgent changes. Why it matters : Ensures project sustainability without renegotiation. Impact on pricing: Usually +3% to +10% applied at the end.
A12: CON 11 | B12: Contigency 11 | C12: 0.01 | D12: Applied at the end for unknowns. What it means : Reserve for unforeseen issues—compliance audits, environment failures, urgent changes. Why it matters : Ensures project sustainability without renegotiation. Impact on pricing: Usually +3% to +10% applied at the end.
A13: CON 12 | B13: Contigency 12 | C13: 0.011 | D13: Applied at the end for unknowns. What it means : Reserve for unforeseen issues—compliance audits, environment failures, urgent changes. Why it matters : Ensures project sustainability without renegotiation. Impact on pricing: Usually +3% to +10% applied at the end.
... A1002: CON 1001 | B1002: Contigency 1001 | C1002: 1 | D1002: Applied at the end for unknowns. What it means : Reserve for unforeseen issues—compliance audits, environment failures, urgent changes. Why it matters : Ensures project sustainability without renegotiation. Impact on pricing: Usually +3% to +10% applied at the end.
